webservice_foundation/__init__.py
webservice_foundation/baserequest.py
webservice_foundation/bodydata.py
webservice_foundation/caseInsensitivedict.py
webservice_foundation/error.py
webservice_foundation/originaljsonencoder.py
webservice_foundation/webservice.py
webservice_foundation-1.0.0.dist-info/METADATA
webservice_foundation-1.0.0.dist-info/WHEEL
webservice_foundation-1.0.0.dist-info/entry_points.txt
webservice_foundation-1.0.0.dist-info/top_level.txt
webservice_foundation-1.0.0.dist-info/RECORD
